raster/__init__.py
raster-0.0.4.dist-info/LICENSE
raster-0.0.4.dist-info/METADATA
raster-0.0.4.dist-info/WHEEL
raster-0.0.4.dist-info/top_level.txt
raster-0.0.4.dist-info/RECORD
