Metadata-Version: 2.1
Name: raster
Version: 0.0.4
Summary: A small package for raster analysis
Home-page: https://github.com/spjace/raster
Author: Shen Pengju
Author-email: spjace@sina.com
Classifier: Programming Language :: Python :: 3
Classifier: License :: OSI Approved :: MIT License
Classifier: Operating System :: OS Independent
Requires-Python: >=3.7
License-File: LICENSE
Requires-Dist: GDAL
Requires-Dist: numpy
Requires-Dist: phenology
Requires-Dist: xarray
